cut2min_bucket/__init__.py
cut2min_bucket/dataset.py
cut2min_bucket/samplers.py
cut2min_bucket-0.1.3.dist-info/licenses/LICENSE
cut2min_bucket-0.1.3.dist-info/METADATA
cut2min_bucket-0.1.3.dist-info/WHEEL
cut2min_bucket-0.1.3.dist-info/top_level.txt
cut2min_bucket-0.1.3.dist-info/RECORD
