Metadata-Version: 2.4
Name: cut2min-bucket
Version: 0.1.3
Summary: A PyTorch Batch Sampler that buckets by input length and cuts to min size in batch
Home-page: https://github.com/gdewael/cut2min-bucket
Author: Gaetan De Waele
Author-email: gaetandewaele@hotmail.com
Requires-Python: >=3.9
License-File: LICENSE
Requires-Dist: numpy
Requires-Dist: torch
Dynamic: license-file
